Metadata-Version: 1.0
Name: dsnd-probability-2022-01-14
Version: 0.1
Summary: Gaussian and Binomial Distribution
Home-page: UNKNOWN
Author: UNKNOWN
Author-email: UNKNOWN
License: UNKNOWN
Platform: UNKNOWN
